ink_wizard/__init__.py
ink_wizard/commands/__init__.py
ink_wizard/commands/base.py
ink_wizard/commands/flipper.py
ink_wizard/commands/psp22.py
ink_wizard/commands/psp34.py
ink_wizard/commands/psp37.py
ink_wizard/commands/template_select.py
ink_wizard/main.py
ink_wizard/template_generators/__init__.py
ink_wizard/template_generators/base.py
ink_wizard/template_generators/flipper.py
ink_wizard/template_generators/psp22.py
ink_wizard/template_generators/psp34.py
ink_wizard/template_generators/psp37.py
ink_wizard/templates/flipper/cargo.txt
ink_wizard/templates/flipper/flipper.txt
ink_wizard/templates/psp22/cargo.txt
ink_wizard/templates/psp22/psp22.txt
ink_wizard/templates/psp34/cargo.txt
ink_wizard/templates/psp34/psp34.txt
ink_wizard/templates/psp37/cargo.txt
ink_wizard/templates/psp37/psp37.txt
ink_wizard-0.1.6.dist-info/entry_points.txt
ink_wizard-0.1.6.dist-info/LICENSE
ink_wizard-0.1.6.dist-info/WHEEL
ink_wizard-0.1.6.dist-info/METADATA
ink_wizard-0.1.6.dist-info/RECORD
