Metadata-Version: 2.1
Name: ink-wizard
Version: 0.1.6
Summary: Ink Wizard is a CLI tool used to scaffold Flipper, PSP-22, PSP-34, PSP-37 smart contracts. CLI will ask user on what kind of functionality user needs. It will scaffold smart contracts based on user options.
License: Apache-2.0
Author: Aviraj Khare
Author-email: thisisavirajkhare@gmail.com
Requires-Python: >=3.8,<4.0
Classifier: License :: OSI Approved :: Apache Software License
Classifier: Programming Language :: Python :: 3
Classifier: Programming Language :: Python :: 3.8
Classifier: Programming Language :: Python :: 3.9
Classifier: Programming Language :: Python :: 3.10
Requires-Dist: Jinja2 (>=3.1.2,<4.0.0)
Requires-Dist: typer[all] (>=0.7.0,<0.8.0)
